cemotion/__init__.py
cemotion/app.py
cemotion/download.py
cemotion-2.2.3.dist-info/licenses/LICENSE
cemotion-2.2.3.dist-info/METADATA
cemotion-2.2.3.dist-info/WHEEL
cemotion-2.2.3.dist-info/top_level.txt
cemotion-2.2.3.dist-info/RECORD
