Metadata-Version: 2.4
Name: Cemotion
Version: 2.2.3
Summary: Cemotion 是 Python 下的中文 NLP 库，可以进行中文情感倾向分析、通用领域中文分词。
Author: Cyberbolt
Author-email: dtconlyone@gmail.com
License: MIT
Project-URL: Homepage, https://github.com/Cyberbolt/Cemotion
Requires-Python: <3.11,>=3.7
License-File: LICENSE
Requires-Dist: tqdm>=4.64.1
Requires-Dist: joblib>=1.0.0
Requires-Dist: requests>=2.25.1
Requires-Dist: numpy>=1.19.5
Requires-Dist: torch<2.1.0,>=2.0.0
Requires-Dist: transformers>=4.24.0
Requires-Dist: modelscope>=1.14.0
Dynamic: author
Dynamic: author-email
Dynamic: license-file
